controlpi/__init__.py
controlpi/main.py
controlpi/motor_controller.py
zenbot/__init__.py
zenbot/main.py
zenbot/motor_controller.py
zenbot_pi-0.1.1.dist-info/licenses/LICENSE
zenbot_pi-0.1.1.dist-info/METADATA
zenbot_pi-0.1.1.dist-info/WHEEL
zenbot_pi-0.1.1.dist-info/entry_points.txt
zenbot_pi-0.1.1.dist-info/top_level.txt
zenbot_pi-0.1.1.dist-info/RECORD
