Metadata-Version: 2.4
Name: zenbot-pi
Version: 0.1.1
Summary: I2C Motor Controller for Raspberry Pi/Arduino robots
Home-page: https://github.com/enkhbold470
Author: Inky Ganbold
Author-email: enkhbold470@gmail.com
Project-URL: Bug Tracker, https://github.com/enkhbold470/rpi-arduino-motor-rx/issues
Classifier: Programming Language :: Python :: 3
Classifier: License :: OSI Approved :: MIT License
Classifier: Operating System :: POSIX :: Linux
Classifier: Topic :: System :: Hardware
Classifier: Topic :: Software Development :: Libraries
Classifier: Intended Audience :: Developers
Classifier: Intended Audience :: Education
Requires-Python: >=3.6
License-File: LICENSE
Requires-Dist: smbus2>=0.4.2
Dynamic: author
Dynamic: author-email
Dynamic: classifier
Dynamic: description
Dynamic: description-content-type
Dynamic: home-page
Dynamic: license-file
Dynamic: project-url
Dynamic: requires-dist
Dynamic: requires-python
Dynamic: summary
